[{"CycleId":1,"CycleDesc":"Monthly Salary","Enabled":true,"DateCaptured":45812.58508498842,"CapturerId":202,"DateModified":null,"ModifierId":null,"CycleTypeId":1,"SkipInNewTaxYear":false},{"CycleId":2,"CycleDesc":"Monthly Salary Temps","Enabled":true,"DateCaptured":45812.58557415509,"CapturerId":202,"DateModified":null,"ModifierId":null,"CycleTypeId":1,"SkipInNewTaxYear":false},{"CycleId":3,"CycleDesc":"Ad Hoc Termination","Enabled":true,"DateCaptured":45813.62048344907,"CapturerId":202,"DateModified":45813.626800578706,"ModifierId":202,"CycleTypeId":1,"SkipInNewTaxYear":false},{"CycleId":4,"CycleDesc":"Fortnight Wages","Enabled":true,"DateCaptured":45813.62079001158,"CapturerId":202,"DateModified":null,"ModifierId":null,"CycleTypeId":3,"SkipInNewTaxYear":false},{"CycleId":5,"CycleDesc":"Soup Kitchen","Enabled":true,"DateCaptured":45813.621039895836,"CapturerId":202,"DateModified":46051.42864421296,"ModifierId":202,"CycleTypeId":1,"SkipInNewTaxYear":false},{"CycleId":6,"CycleDesc":"Councillors","Enabled":true,"DateCaptured":45813.62965466435,"CapturerId":202,"DateModified":null,"ModifierId":null,"CycleTypeId":1,"SkipInNewTaxYear":false},{"CycleId":8,"CycleDesc":"Ward Committee","Enabled":true,"DateCaptured":46084.543049803244,"CapturerId":202,"DateModified":null,"ModifierId":null,"CycleTypeId":2,"SkipInNewTaxYear":false}]