[{"MOC_ID":2,"SalaryHeadID":10,"Enabled":1,"DateCaptured":43511.48574077546,"CapturerID":2,"DateModified":43539.478240358796,"ModifierID":107,"StartDate":1,"EndDate":2958465,"ProRata":0},{"MOC_ID":3,"SalaryHeadID":11,"Enabled":1,"DateCaptured":43511.48791177083,"CapturerID":2,"DateModified":43539.48640324074,"ModifierID":107,"StartDate":1,"EndDate":2958465,"ProRata":0},{"MOC_ID":4,"SalaryHeadID":30,"Enabled":1,"DateCaptured":43511.51936443287,"CapturerID":2,"DateModified":43539.50643368056,"ModifierID":107,"StartDate":1,"EndDate":2958465,"ProRata":0},{"MOC_ID":5,"SalaryHeadID":41,"Enabled":1,"DateCaptured":43511.541291898146,"CapturerID":2,"DateModified":43511.54525505787,"ModifierID":2,"StartDate":1,"EndDate":2958465,"ProRata":0},{"MOC_ID":6,"SalaryHeadID":42,"Enabled":1,"DateCaptured":43511.54187434028,"CapturerID":2,"DateModified":43517.68888862269,"ModifierID":2,"StartDate":1,"EndDate":2958465,"ProRata":0},{"MOC_ID":7,"SalaryHeadID":100,"Enabled":1,"DateCaptured":43846.73563121528,"CapturerID":1,"DateModified":null,"ModifierID":null,"StartDate":43282,"EndDate":2958465,"ProRata":0},{"MOC_ID":8,"SalaryHeadID":33,"Enabled":1,"DateCaptured":44274.36942318287,"CapturerID":104,"DateModified":null,"ModifierID":null,"StartDate":61,"EndDate":2958465,"ProRata":0},{"MOC_ID":9,"SalaryHeadID":151,"Enabled":1,"DateCaptured":44274.45048371528,"CapturerID":104,"DateModified":null,"ModifierID":null,"StartDate":1,"EndDate":2958465,"ProRata":0},{"MOC_ID":10,"SalaryHeadID":65,"Enabled":1,"DateCaptured":44274.45048371528,"CapturerID":1,"DateModified":null,"ModifierID":null,"StartDate":1,"EndDate":2958465,"ProRata":0},{"MOC_ID":11,"SalaryHeadID":178,"Enabled":1,"DateCaptured":45434.39086828704,"CapturerID":1,"DateModified":null,"ModifierID":null,"StartDate":45413,"EndDate":2958465,"ProRata":0},{"MOC_ID":12,"SalaryHeadID":81,"Enabled":1,"DateCaptured":45497.45274702546,"CapturerID":1,"DateModified":null,"ModifierID":null,"StartDate":45474,"EndDate":2958465,"ProRata":0},{"MOC_ID":13,"SalaryHeadID":48,"Enabled":1,"DateCaptured":45855.843507604164,"CapturerID":202,"DateModified":null,"ModifierID":null,"StartDate":45839,"EndDate":2958465,"ProRata":0},{"MOC_ID":14,"SalaryHeadID":37,"Enabled":1,"DateCaptured":45856.75342241898,"CapturerID":202,"DateModified":null,"ModifierID":null,"StartDate":45839,"EndDate":2958465,"ProRata":0},{"MOC_ID":15,"SalaryHeadID":36,"Enabled":1,"DateCaptured":45856.75592824074,"CapturerID":202,"DateModified":null,"ModifierID":null,"StartDate":1,"EndDate":2958465,"ProRata":0},{"MOC_ID":16,"SalaryHeadID":43,"Enabled":1,"DateCaptured":45863.62006917824,"CapturerID":202,"DateModified":null,"ModifierID":null,"StartDate":45658,"EndDate":2958465,"ProRata":0},{"MOC_ID":17,"SalaryHeadID":34,"Enabled":1,"DateCaptured":45863.660114618055,"CapturerID":202,"DateModified":null,"ModifierID":null,"StartDate":45839,"EndDate":2958465,"ProRata":0},{"MOC_ID":18,"SalaryHeadID":60,"Enabled":1,"DateCaptured":45870.43962511574,"CapturerID":202,"DateModified":null,"ModifierID":null,"StartDate":45717,"EndDate":2958465,"ProRata":0},{"MOC_ID":19,"SalaryHeadID":61,"Enabled":1,"DateCaptured":45870.720564965275,"CapturerID":202,"DateModified":null,"ModifierID":null,"StartDate":45717,"EndDate":2958465,"ProRata":0},{"MOC_ID":20,"SalaryHeadID":62,"Enabled":1,"DateCaptured":45870.72202847222,"CapturerID":202,"DateModified":null,"ModifierID":null,"StartDate":45717,"EndDate":2958465,"ProRata":0},{"MOC_ID":21,"SalaryHeadID":63,"Enabled":1,"DateCaptured":45870.723175810184,"CapturerID":202,"DateModified":null,"ModifierID":null,"StartDate":45717,"EndDate":2958465,"ProRata":0},{"MOC_ID":22,"SalaryHeadID":64,"Enabled":1,"DateCaptured":45870.72406901621,"CapturerID":202,"DateModified":null,"ModifierID":null,"StartDate":45717,"EndDate":2958465,"ProRata":0},{"MOC_ID":23,"SalaryHeadID":67,"Enabled":1,"DateCaptured":45870.72642607639,"CapturerID":202,"DateModified":null,"ModifierID":null,"StartDate":45717,"EndDate":2958465,"ProRata":0},{"MOC_ID":24,"SalaryHeadID":68,"Enabled":1,"DateCaptured":45870.72727870371,"CapturerID":202,"DateModified":null,"ModifierID":null,"StartDate":45717,"EndDate":2958465,"ProRata":0},{"MOC_ID":25,"SalaryHeadID":69,"Enabled":1,"DateCaptured":45870.729088506945,"CapturerID":202,"DateModified":null,"ModifierID":null,"StartDate":45717,"EndDate":2958465,"ProRata":0},{"MOC_ID":26,"SalaryHeadID":70,"Enabled":1,"DateCaptured":45870.731277465275,"CapturerID":202,"DateModified":null,"ModifierID":null,"StartDate":45717,"EndDate":2958465,"ProRata":0},{"MOC_ID":27,"SalaryHeadID":71,"Enabled":1,"DateCaptured":45870.73210829861,"CapturerID":202,"DateModified":null,"ModifierID":null,"StartDate":45717,"EndDate":2958465,"ProRata":0},{"MOC_ID":28,"SalaryHeadID":72,"Enabled":1,"DateCaptured":45870.73359753472,"CapturerID":202,"DateModified":null,"ModifierID":null,"StartDate":45717,"EndDate":2958465,"ProRata":0},{"MOC_ID":29,"SalaryHeadID":74,"Enabled":1,"DateCaptured":45870.7345216088,"CapturerID":202,"DateModified":null,"ModifierID":null,"StartDate":45717,"EndDate":2958465,"ProRata":0},{"MOC_ID":30,"SalaryHeadID":75,"Enabled":1,"DateCaptured":45870.73548001157,"CapturerID":202,"DateModified":null,"ModifierID":null,"StartDate":45717,"EndDate":2958465,"ProRata":0},{"MOC_ID":31,"SalaryHeadID":76,"Enabled":1,"DateCaptured":45870.73618950231,"CapturerID":202,"DateModified":null,"ModifierID":null,"StartDate":45717,"EndDate":2958465,"ProRata":0},{"MOC_ID":32,"SalaryHeadID":73,"Enabled":1,"DateCaptured":45873.42509181713,"CapturerID":202,"DateModified":null,"ModifierID":null,"StartDate":45717,"EndDate":2958465,"ProRata":0},{"MOC_ID":33,"SalaryHeadID":132,"Enabled":1,"DateCaptured":45873.43083237269,"CapturerID":202,"DateModified":null,"ModifierID":null,"StartDate":45839,"EndDate":2958465,"ProRata":0},{"MOC_ID":34,"SalaryHeadID":133,"Enabled":1,"DateCaptured":45873.45238059028,"CapturerID":202,"DateModified":null,"ModifierID":null,"StartDate":45839,"EndDate":2958465,"ProRata":0},{"MOC_ID":35,"SalaryHeadID":118,"Enabled":1,"DateCaptured":45873.52812418981,"CapturerID":202,"DateModified":null,"ModifierID":null,"StartDate":45839,"EndDate":2958465,"ProRata":0},{"MOC_ID":36,"SalaryHeadID":117,"Enabled":1,"DateCaptured":45873.53471597222,"CapturerID":202,"DateModified":null,"ModifierID":null,"StartDate":45839,"EndDate":2958465,"ProRata":0},{"MOC_ID":37,"SalaryHeadID":235,"Enabled":1,"DateCaptured":45873.87560413194,"CapturerID":202,"DateModified":null,"ModifierID":null,"StartDate":45717,"EndDate":2958465,"ProRata":0},{"MOC_ID":38,"SalaryHeadID":236,"Enabled":1,"DateCaptured":45873.88621380787,"CapturerID":202,"DateModified":null,"ModifierID":null,"StartDate":45352,"EndDate":2958465,"ProRata":0},{"MOC_ID":39,"SalaryHeadID":237,"Enabled":1,"DateCaptured":45873.88935883102,"CapturerID":202,"DateModified":null,"ModifierID":null,"StartDate":45717,"EndDate":2958465,"ProRata":0},{"MOC_ID":40,"SalaryHeadID":82,"Enabled":1,"DateCaptured":45880.650570798614,"CapturerID":202,"DateModified":null,"ModifierID":null,"StartDate":45839,"EndDate":2958465,"ProRata":0},{"MOC_ID":41,"SalaryHeadID":80,"Enabled":1,"DateCaptured":45880.65243549769,"CapturerID":202,"DateModified":null,"ModifierID":null,"StartDate":45717,"EndDate":2958465,"ProRata":0},{"MOC_ID":42,"SalaryHeadID":83,"Enabled":1,"DateCaptured":45880.65894637731,"CapturerID":202,"DateModified":null,"ModifierID":null,"StartDate":45717,"EndDate":2958465,"ProRata":0},{"MOC_ID":43,"SalaryHeadID":84,"Enabled":1,"DateCaptured":45880.66114621528,"CapturerID":202,"DateModified":null,"ModifierID":null,"StartDate":45717,"EndDate":2958465,"ProRata":0},{"MOC_ID":44,"SalaryHeadID":85,"Enabled":1,"DateCaptured":45880.66292256944,"CapturerID":202,"DateModified":null,"ModifierID":null,"StartDate":45717,"EndDate":2958465,"ProRata":0},{"MOC_ID":45,"SalaryHeadID":248,"Enabled":1,"DateCaptured":45880.705094247685,"CapturerID":202,"DateModified":null,"ModifierID":null,"StartDate":45717,"EndDate":2958465,"ProRata":0},{"MOC_ID":46,"SalaryHeadID":119,"Enabled":1,"DateCaptured":45887.67542068287,"CapturerID":202,"DateModified":null,"ModifierID":null,"StartDate":45839,"EndDate":2958465,"ProRata":0},{"MOC_ID":47,"SalaryHeadID":123,"Enabled":1,"DateCaptured":45887.70396828704,"CapturerID":202,"DateModified":null,"ModifierID":null,"StartDate":45839,"EndDate":2958465,"ProRata":0},{"MOC_ID":48,"SalaryHeadID":120,"Enabled":1,"DateCaptured":45887.71110011574,"CapturerID":202,"DateModified":null,"ModifierID":null,"StartDate":45839,"EndDate":2958465,"ProRata":0},{"MOC_ID":49,"SalaryHeadID":124,"Enabled":1,"DateCaptured":45887.7131599537,"CapturerID":202,"DateModified":null,"ModifierID":null,"StartDate":45839,"EndDate":2958465,"ProRata":0},{"MOC_ID":50,"SalaryHeadID":129,"Enabled":1,"DateCaptured":45887.71551149306,"CapturerID":202,"DateModified":null,"ModifierID":null,"StartDate":45839,"EndDate":2958465,"ProRata":0},{"MOC_ID":51,"SalaryHeadID":128,"Enabled":1,"DateCaptured":45887.7235008912,"CapturerID":202,"DateModified":null,"ModifierID":null,"StartDate":45839,"EndDate":2958465,"ProRata":0},{"MOC_ID":52,"SalaryHeadID":130,"Enabled":1,"DateCaptured":45888.33370350694,"CapturerID":202,"DateModified":null,"ModifierID":null,"StartDate":45839,"EndDate":2958465,"ProRata":0},{"MOC_ID":53,"SalaryHeadID":131,"Enabled":1,"DateCaptured":45888.338303854165,"CapturerID":202,"DateModified":null,"ModifierID":null,"StartDate":45839,"EndDate":2958465,"ProRata":0},{"MOC_ID":54,"SalaryHeadID":249,"Enabled":1,"DateCaptured":45888.356186377314,"CapturerID":202,"DateModified":null,"ModifierID":null,"StartDate":45717,"EndDate":2958465,"ProRata":0},{"MOC_ID":55,"SalaryHeadID":121,"Enabled":1,"DateCaptured":45888.71815721065,"CapturerID":202,"DateModified":null,"ModifierID":null,"StartDate":45839,"EndDate":2958465,"ProRata":0},{"MOC_ID":56,"SalaryHeadID":122,"Enabled":1,"DateCaptured":45888.72425778935,"CapturerID":202,"DateModified":null,"ModifierID":null,"StartDate":45839,"EndDate":2958465,"ProRata":0},{"MOC_ID":57,"SalaryHeadID":38,"Enabled":1,"DateCaptured":45890.48079047454,"CapturerID":202,"DateModified":null,"ModifierID":null,"StartDate":45839,"EndDate":2958465,"ProRata":0},{"MOC_ID":58,"SalaryHeadID":66,"Enabled":1,"DateCaptured":45891.37453206019,"CapturerID":202,"DateModified":null,"ModifierID":null,"StartDate":45839,"EndDate":2958465,"ProRata":0},{"MOC_ID":59,"SalaryHeadID":211,"Enabled":1,"DateCaptured":45898.330812037035,"CapturerID":202,"DateModified":null,"ModifierID":null,"StartDate":45717,"EndDate":2958465,"ProRata":0},{"MOC_ID":60,"SalaryHeadID":212,"Enabled":1,"DateCaptured":45898.33426408565,"CapturerID":202,"DateModified":null,"ModifierID":null,"StartDate":45717,"EndDate":2958465,"ProRata":0},{"MOC_ID":61,"SalaryHeadID":214,"Enabled":1,"DateCaptured":45898.33828993056,"CapturerID":202,"DateModified":null,"ModifierID":null,"StartDate":45717,"EndDate":2958465,"ProRata":0},{"MOC_ID":62,"SalaryHeadID":210,"Enabled":1,"DateCaptured":45898.5968059838,"CapturerID":202,"DateModified":null,"ModifierID":null,"StartDate":45717,"EndDate":2958465,"ProRata":0},{"MOC_ID":63,"SalaryHeadID":213,"Enabled":1,"DateCaptured":45898.59965239583,"CapturerID":202,"DateModified":null,"ModifierID":null,"StartDate":45717,"EndDate":2958465,"ProRata":0},{"MOC_ID":64,"SalaryHeadID":215,"Enabled":1,"DateCaptured":45898.609625150464,"CapturerID":202,"DateModified":null,"ModifierID":null,"StartDate":45717,"EndDate":2958465,"ProRata":0},{"MOC_ID":65,"SalaryHeadID":216,"Enabled":1,"DateCaptured":45898.610949155096,"CapturerID":202,"DateModified":null,"ModifierID":null,"StartDate":45717,"EndDate":2958465,"ProRata":0},{"MOC_ID":66,"SalaryHeadID":252,"Enabled":1,"DateCaptured":45903.57126153935,"CapturerID":202,"DateModified":null,"ModifierID":null,"StartDate":45717,"EndDate":2958465,"ProRata":0},{"MOC_ID":67,"SalaryHeadID":253,"Enabled":1,"DateCaptured":45903.576015162034,"CapturerID":202,"DateModified":null,"ModifierID":null,"StartDate":45717,"EndDate":2958465,"ProRata":0},{"MOC_ID":68,"SalaryHeadID":52,"Enabled":1,"DateCaptured":45910.59519633102,"CapturerID":202,"DateModified":null,"ModifierID":null,"StartDate":45839,"EndDate":2958465,"ProRata":0},{"MOC_ID":69,"SalaryHeadID":270,"Enabled":1,"DateCaptured":45925.79499598379,"CapturerID":202,"DateModified":null,"ModifierID":null,"StartDate":45717,"EndDate":2958465,"ProRata":0},{"MOC_ID":71,"SalaryHeadID":274,"Enabled":1,"DateCaptured":45926.34148263889,"CapturerID":202,"DateModified":null,"ModifierID":null,"StartDate":45870,"EndDate":45961,"ProRata":0},{"MOC_ID":72,"SalaryHeadID":272,"Enabled":1,"DateCaptured":45926.368438391204,"CapturerID":202,"DateModified":null,"ModifierID":null,"StartDate":45870,"EndDate":45961,"ProRata":0},{"MOC_ID":73,"SalaryHeadID":273,"Enabled":1,"DateCaptured":45926.37235277778,"CapturerID":202,"DateModified":null,"ModifierID":null,"StartDate":45870,"EndDate":45961,"ProRata":0},{"MOC_ID":74,"SalaryHeadID":275,"Enabled":1,"DateCaptured":45926.75538429398,"CapturerID":202,"DateModified":null,"ModifierID":null,"StartDate":45870,"EndDate":2958465,"ProRata":0},{"MOC_ID":75,"SalaryHeadID":276,"Enabled":1,"DateCaptured":45937.40819829861,"CapturerID":202,"DateModified":null,"ModifierID":null,"StartDate":45717,"EndDate":2958465,"ProRata":0},{"MOC_ID":76,"SalaryHeadID":277,"Enabled":1,"DateCaptured":45937.444014699075,"CapturerID":202,"DateModified":null,"ModifierID":null,"StartDate":45717,"EndDate":2958465,"ProRata":0},{"MOC_ID":77,"SalaryHeadID":393,"Enabled":1,"DateCaptured":45950.60551061342,"CapturerID":202,"DateModified":null,"ModifierID":null,"StartDate":45717,"EndDate":45961,"ProRata":0},{"MOC_ID":78,"SalaryHeadID":428,"Enabled":1,"DateCaptured":45964.617624502316,"CapturerID":202,"DateModified":null,"ModifierID":null,"StartDate":45717,"EndDate":2958465,"ProRata":0},{"MOC_ID":79,"SalaryHeadID":0,"Enabled":1,"DateCaptured":45972.6229130787,"CapturerID":202,"DateModified":null,"ModifierID":null,"StartDate":45717,"EndDate":2958465,"ProRata":0},{"MOC_ID":80,"SalaryHeadID":435,"Enabled":1,"DateCaptured":45972.66311412037,"CapturerID":202,"DateModified":null,"ModifierID":null,"StartDate":45717,"EndDate":2958465,"ProRata":0},{"MOC_ID":81,"SalaryHeadID":436,"Enabled":1,"DateCaptured":45972.67869586805,"CapturerID":202,"DateModified":null,"ModifierID":null,"StartDate":45717,"EndDate":2958465,"ProRata":0},{"MOC_ID":82,"SalaryHeadID":86,"Enabled":1,"DateCaptured":45973.67670740741,"CapturerID":202,"DateModified":null,"ModifierID":null,"StartDate":1,"EndDate":2958465,"ProRata":0},{"MOC_ID":83,"SalaryHeadID":39,"Enabled":1,"DateCaptured":45974.35398741898,"CapturerID":202,"DateModified":null,"ModifierID":null,"StartDate":45839,"EndDate":2958465,"ProRata":0},{"MOC_ID":84,"SalaryHeadID":443,"Enabled":1,"DateCaptured":45981.45938359954,"CapturerID":202,"DateModified":null,"ModifierID":null,"StartDate":45717,"EndDate":2958465,"ProRata":0},{"MOC_ID":85,"SalaryHeadID":241,"Enabled":1,"DateCaptured":46001.609666550925,"CapturerID":4302,"DateModified":null,"ModifierID":null,"StartDate":45992,"EndDate":2958465,"ProRata":0},{"MOC_ID":86,"SalaryHeadID":433,"Enabled":1,"DateCaptured":46051.57111828704,"CapturerID":202,"DateModified":null,"ModifierID":null,"StartDate":46023,"EndDate":2958465,"ProRata":0},{"MOC_ID":87,"SalaryHeadID":491,"Enabled":1,"DateCaptured":46078.44049811343,"CapturerID":202,"DateModified":null,"ModifierID":null,"StartDate":45839,"EndDate":2958465,"ProRata":0},{"MOC_ID":88,"SalaryHeadID":492,"Enabled":1,"DateCaptured":46078.45613619213,"CapturerID":202,"DateModified":null,"ModifierID":null,"StartDate":45839,"EndDate":2958465,"ProRata":0}]